pdflatex/__init__.py
pdflatex/pdflatex.py
pdflatex-0.1.2.dist-info/LICENSE
pdflatex-0.1.2.dist-info/WHEEL
pdflatex-0.1.2.dist-info/METADATA
pdflatex-0.1.2.dist-info/RECORD
