Metadata-Version: 2.1
Name: pdflatex
Version: 0.1.2
Summary: Simple wrapper to calling pdflatex
Home-page: https://github.com/mbello/pdflatex
License: UNKNOWN
Keywords: pdflatex,pypdflatex,latex to pdf using python
Author: mbello
Author-email: mbello@users.noreply.github.com
Requires-Python: >=3.6,<4.0
Classifier: Programming Language :: Python :: 3
Classifier: Programming Language :: Python :: 3.6
Classifier: Programming Language :: Python :: 3.7
Requires-Dist: attrs (>=18.2,<19.0)
Project-URL: Repository, https://github.com/mbello/pdflatex
